include/armadillo
include/armadillo_bits/op_powmat_meat.hpp
include/armadillo_bits/spglue_plus_bones.hpp
include/armadillo_bits/op_logmat_meat.hpp
include/armadillo_bits/op_prod_bones.hpp
include/armadillo_bits/fn_sort.hpp
include/armadillo_bits/op_cx_scalar_bones.hpp
include/armadillo_bits/fn_index_max.hpp
include/armadillo_bits/op_sum_bones.hpp
include/armadillo_bits/fn_numel.hpp
include/armadillo_bits/csv_name.hpp
include/armadillo_bits/op_htrans_bones.hpp
include/armadillo_bits/glue_times_misc_meat.hpp
include/armadillo_bits/op_rcond_meat.hpp
include/armadillo_bits/fn_orth_null.hpp
include/armadillo_bits/op_cov_meat.hpp
include/armadillo_bits/op_relational_bones.hpp
include/armadillo_bits/wall_clock_bones.hpp
include/armadillo_bits/spglue_times_meat.hpp
include/armadillo_bits/glue_trapz_bones.hpp
include/armadillo_bits/fn_sylvester.hpp
include/armadillo_bits/glue_affmul_meat.hpp
include/armadillo_bits/op_elem_bones.hpp
include/armadillo_bits/glue_join_meat.hpp
include/armadillo_bits/glue_cov_bones.hpp
include/armadillo_bits/op_cumprod_bones.hpp
include/armadillo_bits/fn_rank.hpp
include/armadillo_bits/fn_trig.hpp
include/armadillo_bits/op_det_bones.hpp
include/armadillo_bits/spglue_kron_bones.hpp
include/armadillo_bits/op_norm2est_meat.hpp
include/armadillo_bits/fn_all.hpp
include/armadillo_bits/eglue_core_meat.hpp
include/armadillo_bits/spop_relational_bones.hpp
include/armadillo_bits/op_sort_bones.hpp
include/armadillo_bits/subview_cube_bones.hpp
include/armadillo_bits/spop_trimat_meat.hpp
include/armadillo_bits/spop_strans_bones.hpp
include/armadillo_bits/spop_repmat_meat.hpp
include/armadillo_bits/fn_eig_pair.hpp
include/armadillo_bits/fn_trace.hpp
include/armadillo_bits/promote_type.hpp
include/armadillo_bits/fn_wishrnd.hpp
include/armadillo_bits/op_row_as_mat_meat.hpp
include/armadillo_bits/MapMat_meat.hpp
include/armadillo_bits/access.hpp
include/armadillo_bits/SpBase_bones.hpp
ppca_py-1.0.3.dist-info/RECORD
ppca_py-1.0.3.dist-info/WHEEL
ppca_py-1.0.3.dist-info/METADATA
ppca_py-1.0.3.dist-info/licenses/LICENSE
