Metadata-Version: 2.2
Name: ppca-py
Version: 1.0.3
Summary: Probabilistic PCA (PPCA) with missing-data support - fast C++ core, clean Python API
Keywords: ppca,probabilistic pca,dimensionality reduction,missing data
Author: brdav
License: MIT License
Classifier: Programming Language :: Python :: 3
Classifier: Programming Language :: Python :: 3.9
Classifier: Programming Language :: Python :: 3.10
Classifier: Programming Language :: Python :: 3.11
Classifier: Programming Language :: C++
Classifier: License :: OSI Approved :: MIT License
Classifier: Operating System :: OS Independent
Classifier: Topic :: Scientific/Engineering :: Artificial Intelligence
Classifier: Topic :: Scientific/Engineering :: Mathematics
Project-URL: Homepage, https://github.com/brdav/ppca-cpp
Project-URL: Source, https://github.com/brdav/ppca-cpp
Requires-Python: >=3.9
Requires-Dist: numpy>=1.22
Provides-Extra: dev
Requires-Dist: pytest>=7; extra == "dev"
Requires-Dist: build; extra == "dev"
Requires-Dist: wheel; extra == "dev"
Requires-Dist: packaging; extra == "dev"
Requires-Dist: scikit-learn>=1.7.1; extra == "dev"
Requires-Dist: pre-commit; extra == "dev"
